multithreader/__init__.py
multithreader/__init__.pyi
multithreader/__main__.py
multithreader/__main__.pyi
multithreader/py.typed
multithreader-1.0.5.dist-info/METADATA
multithreader-1.0.5.dist-info/WHEEL
multithreader-1.0.5.dist-info/RECORD
