Metadata-Version: 2.1
Name: multithreader
Version: 1.0.5
Summary: Execute Python functions with multithreading.
Home-page: https://gitlab.com/fer1035_python/modules/pypi-multithreader
License: GPL-2.0-only
Keywords: multithreading,functions,threading,parallel,concurrent
Author: Ahmad Ferdaus Abd Razak
Author-email: ahmad.ferdaus.abd.razak@ni.com
Requires-Python: >=3.9,<4.0
Classifier: License :: OSI Approved :: GNU General Public License v2 (GPLv2)
Classifier: Programming Language :: Python :: 3
Classifier: Programming Language :: Python :: 3.9
Classifier: Programming Language :: Python :: 3.10
Classifier: Programming Language :: Python :: 3.11
Classifier: Programming Language :: Python :: 3.12
Project-URL: Repository, https://gitlab.com/fer1035_python/modules/pypi-multithreader
